[
  {
    "id": "c816bd155f7747524492e431040ad8ce",
    "email": "robert.hunt@owlservices.com",
    "password": "080491Rh!",
    "label": "Robert Hunt",
    "lastUsed": "2025-05-06T20:06:50.314Z",
    "friendlyName": "Robert"
  },
  {
    "id": "7bea3bdb7e8e303eacaba442bd824004",
    "email": "bruce.hunt@owlservices.com",
    "password": "Crompco0511",
    "label": "Bruce Hunt",
    "lastUsed": "2025-05-07T16:37:53.627Z",
    "friendlyName": "Bruce",
    "notificationSettings": {
      "email": {
        "enabled": true,
        "frequency": "immediate",
        "deliveryTime": "18:00"
      },
      "pushover": {
        "enabled": true
      },
      "enabled": true
    },
    "configuredEmail": "bruce.hunt@owlservices.com"
  }
]